pispy/__init__.py
pispy/__main__.py
pispy/app.py
pispy/py.typed
pispy/data/__init__.py
pispy/data/package.py
pispy/widgets/__init__.py
pispy/widgets/package_information.py
pispy_client-1.0.0.dist-info/METADATA
pispy_client-1.0.0.dist-info/WHEEL
pispy_client-1.0.0.dist-info/entry_points.txt
pispy_client-1.0.0.dist-info/licenses/LICENSE
pispy_client-1.0.0.dist-info/RECORD
