Metadata-Version: 2.3
Name: pispy-client
Version: 1.0.0
Summary: A terminal-based Python package index inspector
Project-URL: Homepage, https://github.com/davep/pispy
Project-URL: Repository, https://github.com/davep/pispy
Project-URL: Documentation, https://github.com/davep/pispy/blob/main/README.md
Project-URL: Source, https://github.com/davep/pispy
Project-URL: Issues, https://github.com/davep/pispy/issues
Project-URL: Discussions, https://github.com/davep/pispy/discussions
Author-email: Dave Pearson <davep@davep.org>
License: License :: OSI Approved :: GNU General Public License v3 or later (GPLv3+)
Classifier: Development Status :: 5 - Production/Stable
Classifier: Environment :: Console
Classifier: Intended Audience :: End Users/Desktop
Classifier: License :: OSI Approved :: GNU General Public License v3 or later (GPLv3+)
Classifier: Natural Language :: English
Classifier: Operating System :: OS Independent
Classifier: Programming Language :: Python :: 3.10
Classifier: Programming Language :: Python :: 3.11
Classifier: Programming Language :: Python :: 3.12
Classifier: Programming Language :: Python :: 3.13
Classifier: Topic :: Internet
Classifier: Topic :: Terminals
Classifier: Typing :: Typed
Requires-Python: >=3.10
Requires-Dist: httpx
Requires-Dist: packaging
Requires-Dist: textual>=3.1.0
